binaryrain_helper_data_processing/__init__.py
binaryrain_helper_data_processing/dataframe.py
binaryrain_helper_data_processing-0.1.2.dist-info/licenses/LICENSE
binaryrain_helper_data_processing-0.1.2.dist-info/METADATA
binaryrain_helper_data_processing-0.1.2.dist-info/WHEEL
binaryrain_helper_data_processing-0.1.2.dist-info/top_level.txt
binaryrain_helper_data_processing-0.1.2.dist-info/RECORD
