Metadata-Version: 2.4
Name: binaryrain-helper-data-processing
Version: 0.1.2
Summary: Aims to simplify and help with commonly used functions in the data processing areas.
Author: Binary Rain, Marcel T.O
Project-URL: Homepage, https://binaryrain-net.github.io/Binary-Rain-Helper-Toolkit/
Keywords: binary rain,common,help,functions,data processing,dataframe
Classifier: Programming Language :: Python
Classifier: Programming Language :: Python :: 3
Requires-Python: >=3.10
License-File: LICENSE
Requires-Dist: pandas>=2.3.3
Requires-Dist: pyarrow>=22.0.0
Requires-Dist: pytest>=8.4.2
Requires-Dist: pytest-cov>=7.0.0
Dynamic: license-file
